bin/__init__.py
exploratium/__init__.py
exploratium/quant.py
exploratium_quant-0.0.3.data/scripts/quant-cli
utils/__init__.py
utils/datafetcher.py
exploratium_quant-0.0.3.dist-info/LICENSE
exploratium_quant-0.0.3.dist-info/METADATA
exploratium_quant-0.0.3.dist-info/WHEEL
exploratium_quant-0.0.3.dist-info/top_level.txt
exploratium_quant-0.0.3.dist-info/RECORD
