Metadata-Version: 2.1
Name: exploratium-quant
Version: 0.0.3
Summary: ETL library to download and pre-process financial data.
Home-page: https://github.com/exploratium/quant-cli
Author: Carlos Rivera
Author-email: carlos@synx.ai
License: UNKNOWN
Project-URL: Bug Tracker, https://github.com/exploratium/quant-cli/issues
Platform: UNKNOWN
Classifier: Programming Language :: Python :: 3
Classifier: License :: OSI Approved :: MIT License
Classifier: Operating System :: OS Independent
Requires-Python: >=3.6
Requires-Dist: click
Requires-Dist: blessed
Requires-Dist: pandas-datareader
